angelslim/__init__.py
angelslim/engine.py
angelslim/compressor/__init__.py
angelslim/compressor/compressor_factory.py
angelslim/compressor/diffusion/__init__.py
angelslim/compressor/diffusion/cache/__init__.py
angelslim/compressor/diffusion/cache/cache_helper.py
angelslim/compressor/diffusion/cache/deepcache_helper.py
angelslim/compressor/diffusion/cache/taylorcache_helper.py
angelslim/compressor/diffusion/cache/teacache_helper.py
angelslim/compressor/diffusion/kernels/__init__.py
angelslim/compressor/diffusion/kernels/python/__init__.py
angelslim/compressor/diffusion/kernels/python/gemm/__init__.py
angelslim/compressor/diffusion/kernels/python/gemm/fp8_gemm.py
angelslim/compressor/diffusion/kernels/python/quantizers/__init__.py
angelslim/compressor/diffusion/kernels/python/quantizers/fp8_per_block.py
angelslim/compressor/diffusion/kernels/python/quantizers/fp8_per_token_group.py
angelslim/compressor/diffusion/quant/__init__.py
angelslim/compressor/diffusion/quant/ptq.py
angelslim/compressor/diffusion/quant/quant_func.py
angelslim/compressor/diffusion/quant/modules/__init__.py
angelslim/compressor/diffusion/quant/modules/linear.py
angelslim/compressor/diffusion/quant/utils/__init__.py
angelslim/compressor/diffusion/quant/utils/quant_io.py
angelslim/compressor/diffusion/quant/utils/utils.py
angelslim/compressor/distill/__init__.py
angelslim/compressor/quant/__init__.py
angelslim/compressor/quant/ptq.py
angelslim/compressor/quant/core/__init__.py
angelslim/compressor/quant/core/config.py
angelslim/compressor/quant/core/fp8_analyse_tools.py
angelslim/compressor/quant/core/hook.py
angelslim/compressor/quant/core/metrics.py
angelslim/compressor/quant/core/packing_utils.py
angelslim/compressor/quant/core/quant_func.py
angelslim/compressor/quant/core/sample_func.py
angelslim/compressor/quant/core/save.py
angelslim/compressor/quant/modules/__init__.py
angelslim/compressor/quant/modules/catcher.py
angelslim/compressor/quant/modules/helper_layer.py
angelslim-0.3.0.dist-info/licenses/LICENSE
angelslim-0.3.0.dist-info/METADATA
angelslim-0.3.0.dist-info/WHEEL
angelslim-0.3.0.dist-info/top_level.txt
angelslim-0.3.0.dist-info/RECORD
