Metadata-Version: 2.4
Name: angelslim
Version: 0.3.0
Summary: A toolkit for compress llm model.
Home-page: https://github.com/Tencent/AngelSlim
Author: Tencent Author
License: License for AngelSlim
Keywords: Tencent large language model model-optimize compression toolkit.
Classifier: Development Status :: 4 - Beta
Classifier: Intended Audience :: Developers
Classifier: Intended Audience :: Education
Classifier: Intended Audience :: Science/Research
Classifier: License :: OSI Approved :: Apache Software License
Classifier: Programming Language :: Python :: 3.8
Classifier: Programming Language :: Python :: 3.9
Classifier: Programming Language :: Python :: 3.10
Classifier: Programming Language :: Python :: 3.12
Classifier: Topic :: Scientific/Engineering
Classifier: Topic :: Scientific/Engineering :: Mathematics
Classifier: Topic :: Scientific/Engineering :: Artificial Intelligence
Classifier: Topic :: Software Development
Classifier: Topic :: Software Development :: Libraries
Classifier: Topic :: Software Development :: Libraries :: Python Modules
Requires-Python: >=3.0
License-File: LICENSE
Requires-Dist: torch>=2.6.0
Requires-Dist: torchvision>=0.21.0
Requires-Dist: transformers>=4.57.1
Requires-Dist: safetensors>=0.5.3
Requires-Dist: numpy
Requires-Dist: tqdm
Requires-Dist: triton
Requires-Dist: pyarrow
Requires-Dist: tiktoken
Requires-Dist: datasets
Requires-Dist: threadpoolctl
Requires-Dist: shortuuid
Requires-Dist: accelerate
Provides-Extra: all
Requires-Dist: fschat; extra == "all"
Requires-Dist: openai; extra == "all"
Requires-Dist: anthropic; extra == "all"
Requires-Dist: ray; extra == "all"
Requires-Dist: referencing; extra == "all"
Requires-Dist: jsonschema_specifications; extra == "all"
Requires-Dist: deepspeed; extra == "all"
Requires-Dist: wandb==0.22.1; extra == "all"
Requires-Dist: diffusers>=0.34.0; extra == "all"
Requires-Dist: qwen_vl_utils==0.0.11; extra == "all"
Requires-Dist: qwen_omni_utils; extra == "all"
Requires-Dist: torchaudio; extra == "all"
Requires-Dist: openai-whisper; extra == "all"
Requires-Dist: onnxruntime-gpu; extra == "all"
Requires-Dist: inflect; extra == "all"
Requires-Dist: wetext; extra == "all"
Requires-Dist: librosa; extra == "all"
Requires-Dist: mistral_common; extra == "all"
Requires-Dist: vllm>=0.11.0; extra == "all"
Provides-Extra: speculative
Requires-Dist: fschat; extra == "speculative"
Requires-Dist: openai; extra == "speculative"
Requires-Dist: anthropic; extra == "speculative"
Requires-Dist: ray; extra == "speculative"
Requires-Dist: referencing; extra == "speculative"
Requires-Dist: jsonschema_specifications; extra == "speculative"
Requires-Dist: deepspeed; extra == "speculative"
Requires-Dist: wandb==0.22.1; extra == "speculative"
Provides-Extra: diffusion
Requires-Dist: diffusers>=0.34.0; extra == "diffusion"
Provides-Extra: multimodal
Requires-Dist: qwen_vl_utils==0.0.11; extra == "multimodal"
Requires-Dist: qwen_omni_utils; extra == "multimodal"
Requires-Dist: torchaudio; extra == "multimodal"
Requires-Dist: openai-whisper; extra == "multimodal"
Requires-Dist: onnxruntime-gpu; extra == "multimodal"
Requires-Dist: inflect; extra == "multimodal"
Requires-Dist: wetext; extra == "multimodal"
Requires-Dist: librosa; extra == "multimodal"
Requires-Dist: mistral_common; extra == "multimodal"
Provides-Extra: benchmark
Requires-Dist: vllm>=0.11.0; extra == "benchmark"
Dynamic: author
Dynamic: classifier
Dynamic: description
Dynamic: home-page
Dynamic: keywords
Dynamic: license
Dynamic: license-file
Dynamic: provides-extra
Dynamic: requires-dist
Dynamic: requires-python
Dynamic: summary
